<annotation>
	<folder>n07753592</folder>
	<filename>n07753592_2099</filename>
	<source>
		<database>ImageNet database</database>
	</source>
	<size>
		<width>500</width>
		<height>333</height>
		<depth>3</depth>
	</size>
	<segmented>0</segmented>
	<object>
		<name>n07753592</name>
		<pose>Unspecified</pose>
		<truncated>0</truncated>
		<difficult>0</difficult>
		<bndbox>
			<xmin>192</xmin>
			<ymin>56</ymin>
			<xmax>499</xmax>
			<ymax>275</ymax>
		</bndbox>
	</object>
	<object>
		<name>n07753592</name>
		<pose>Unspecified</pose>
		<truncated>0</truncated>
		<difficult>0</difficult>
		<bndbox>
			<xmin>180</xmin>
			<ymin>75</ymin>
			<xmax>471</xmax>
			<ymax>332</ymax>
		</bndbox>
	</object>
	<object>
		<name>n07753592</name>
		<pose>Unspecified</pose>
		<truncated>0</truncated>
		<difficult>0</difficult>
		<bndbox>
			<xmin>174</xmin>
			<ymin>114</ymin>
			<xmax>454</xmax>
			<ymax>331</ymax>
		</bndbox>
	</object>
</annotation>